{
  "gallery": [
    {
      "filename": "pink-dress-1.jpeg",
      "alt": "",
      "altEn": "",
      "title": "",
      "titleEn": ""
    },
    {
      "filename": "pink-dress-2.jpeg",
      "alt": "Kolekcia ružových šiat na vešiakoch v MagicRoom.",
      "altEn": "Collection of pink dresses on hangers at MagicRoom.",
      "title": "Výber šiat",
      "titleEn": "Dress selection"
    },
    {
      "filename": "pink-dress-3.jpeg",
      "alt": "Detail jemnej látky a strihu ružových šiat.",
      "altEn": "Detail of delicate fabric and cut of pink dresses.",
      "title": "Jemné detaily",
      "titleEn": "Soft details"
    },
    {
      "filename": "pink-dress-4.jpeg",
      "alt": "Spoločenské šaty v odtieňoch púdrovej ružovej.",
      "altEn": "Formal dresses in shades of powder pink.",
      "title": "Púdrová ružová",
      "titleEn": "Powder pink"
    },
    {
      "filename": "pink-dress-5.jpeg",
      "alt": "Svadobné šaty na vešiaku v MagicRoom.",
      "altEn": "Wedding dresses on a hanger at MagicRoom.",
      "title": "Šaty na mieru",
      "titleEn": "Custom dresses"
    },
    {
      "filename": "pink-dress-6.jpeg",
      "alt": "Prehliadka ružových spoločenských šiat v salóne.",
      "altEn": "Showcase of pink formal dresses in the salon.",
      "title": "Večerná móda",
      "titleEn": "Evening fashion"
    },
    {
      "filename": "purple-dress-1.jpeg",
      "alt": "Fialové spoločenské šaty s elegantným strihom.",
      "altEn": "Purple formal dresses with an elegant cut.",
      "title": "Fialová vznešenosť",
      "titleEn": "Purple nobility"
    },
    {
      "filename": "purple-dress-2.jpeg",
      "alt": "Detailné spracovanie fialových spoločenských šiat.",
      "altEn": "Detailed craftsmanship of purple formal dresses.",
      "title": "Večerné šaty",
      "titleEn": "Evening dresses"
    },
    {
      "filename": "purple-dress-3.jpeg",
      "alt": "Moderné fialové šaty pre špeciálne príležitosti.",
      "altEn": "Modern purple dresses for special occasions.",
      "title": "Štýlová fialová",
      "titleEn": "Stylish purple"
    },
    {
      "filename": "interior-warm-1.jpeg",
      "alt": "Interiér svadobného salónu MagicRoom v Martine.",
      "altEn": "Interior of the MagicRoom wedding salon in Martin.",
      "title": "Interiér salónu",
      "titleEn": "Salon interior"
    },
    {
      "filename": "interior-warm-2.jpeg",
      "alt": "Útulná atmosféra v našom salóne pri teplom osvetlení.",
      "altEn": "Cozy atmosphere in our salon with warm lighting.",
      "title": "Príjemné prostredie",
      "titleEn": "Pleasant environment"
    },
    {
      "filename": "interior-warm-3.jpeg",
      "alt": "Pohľad na skúšobné kabínky a zrkadlá v salóne.",
      "altEn": "View of fitting rooms and mirrors in the salon.",
      "title": "Skúšobná zóna",
      "titleEn": "Fitting area"
    },
    {
      "filename": "interior-warm-4.jpeg",
      "alt": "Detail nábytku a výzdoby v interiéri salónu.",
      "altEn": "Detail of furniture and decoration in the salon interior.",
      "title": "Dizajn salónu",
      "titleEn": "Salon design"
    },
    {
      "filename": "interior-warm-5.jpeg",
      "alt": "Priestor pre nevesty a ich doprovod v MagicRoom.",
      "altEn": "Space for brides and their companions at MagicRoom.",
      "title": "Zóna pre hostí",
      "titleEn": "Guest zone"
    },
    {
      "filename": "interior-warm-6.jpeg",
      "alt": "Celkový pohľad na presvetlený interiér salónu.",
      "altEn": "General view of the well-lit salon interior.",
      "title": "Svetlý priestor",
      "titleEn": "Bright space"
    },
    {
      "filename": "interior-warm-7.jpeg",
      "alt": "Elegantne zariadený kútik pre konzultácie.",
      "altEn": "Elegantly furnished corner for consultations.",
      "title": "Konzultačný kútik",
      "titleEn": "Consultation corner"
    },
    {
      "filename": "interior-cold-1.jpeg",
      "alt": "Pohľad na salón MagicRoom.",
      "altEn": "View of the MagicRoom salon.",
      "title": "Náš priestor",
      "titleEn": "Our space"
    },
    {
      "filename": "interior-cold-2.jpeg",
      "alt": "Moderný interiér salónu v neutrálnych tónoch.",
      "altEn": "Modern salon interior in neutral tones.",
      "title": "Moderný štýl",
      "titleEn": "Modern style"
    },
    {
      "filename": "interior-cold-3.jpeg",
      "alt": "Minimalistický dizajn predajnej plochy.",
      "altEn": "Minimalist design of the sales floor.",
      "title": "Čisté línie",
      "titleEn": "Clean lines"
    },
    {
      "filename": "interior-cold-4.jpeg",
      "alt": "Usporiadanie šiat v modernom salóne.",
      "altEn": "Dress arrangement in a modern salon.",
      "title": "Organizácia salónu",
      "titleEn": "Salon organization"
    },
    {
      "filename": "interior-neutral-1.jpeg",
      "alt": "Prirodzené osvetlenie v interiéri MagicRoom.",
      "altEn": "Natural lighting in the MagicRoom interior.",
      "title": "Prirodzené svetlo",
      "titleEn": "Natural light"
    },
    {
      "filename": "chessboard-contrast-1.jpeg",
      "alt": "Čierno-biela šachovnicová podlaha v salóne.",
      "altEn": "Black and white checkered floor in the salon.",
      "title": "Šachovnicový vzor",
      "titleEn": "Checkered pattern"
    },
    {
      "filename": "chessboard-contrast-2.jpeg",
      "alt": "Detail šachovnicovej podlahy pod vešiakmi.",
      "altEn": "Detail of checkered floor under the hangers.",
      "title": "Štýlový interiér",
      "titleEn": "Stylish interior"
    },
    {
      "filename": "chessboard-contrast-3.jpeg",
      "alt": "Hra svetla a tieňa na šachovnicovej podlahe.",
      "altEn": "Play of light and shadow on the checkered floor.",
      "title": "Umelecký detail",
      "titleEn": "Artistic detail"
    },
    {
      "filename": "chessboard-contrast-4.jpeg",
      "alt": "Pohľad na priestor salónu s výraznou podlahou.",
      "altEn": "View of the salon space with distinctive flooring.",
      "title": "Výrazný dizajn",
      "titleEn": "Distinctive design"
    },
    {
      "filename": "chessboard-contrast-5.jpeg",
      "alt": "Kombinácia šachovnice a bieleho nábytku.",
      "altEn": "Combination of checkered pattern and white furniture.",
      "title": "Kontrastný interiér",
      "titleEn": "Contrast interior"
    },
    {
      "filename": "chessboard-light-1.jpeg",
      "alt": "Svetlejšia varianta šachovnicovej podlahy v MagicRoom.",
      "altEn": "Lighter version of the checkered floor at MagicRoom.",
      "title": "Svetlá podlaha",
      "titleEn": "Light flooring"
    },
    {
      "filename": "chessboard-light-2.jpeg",
      "alt": "Detailný pohľad na povrch svetlej podlahy.",
      "altEn": "Detailed view of the light floor surface.",
      "title": "Povrch podlahy",
      "titleEn": "Floor surface"
    },
    {
      "filename": "chessboard-light-3.jpeg",
      "alt": "Presvetlená časť salónu so svetlým vzorom.",
      "altEn": "Well-lit part of the salon with a light pattern.",
      "title": "Jasný interiér",
      "titleEn": "Bright interior"
    },
    {
      "filename": "chessboard-light-4.jpeg",
      "alt": "Moderné riešenie podlahy v svadobnom štúdiu.",
      "altEn": "Modern flooring solution in the wedding studio.",
      "title": "Podlahový dizajn",
      "titleEn": "Floor design"
    },
    {
      "filename": "dark-detail-1.jpeg",
      "alt": "Detailný pohľad na tmavé prvky interiéru.",
      "altEn": "Detailed view of dark interior elements.",
      "title": "Tmavý detail",
      "titleEn": "Dark detail"
    },
    {
      "filename": "dark-detail-2.jpeg",
      "alt": "Detail textúry a materiálov v MagicRoom.",
      "altEn": "Detail of texture and materials at MagicRoom.",
      "title": "Materiály",
      "titleEn": "Materials"
    },
    {
      "filename": "dark-detail-3.jpeg",
      "alt": "Kombinácia materiálov v tmavších odtieňoch.",
      "altEn": "Combination of materials in darker shades.",
      "title": "Textúry",
      "titleEn": "Textures"
    },
    {
      "filename": "dark-detail-4.jpeg",
      "alt": "Zameranie na drobné detaily výzdoby.",
      "altEn": "Focus on small decoration details.",
      "title": "Drobné detaily",
      "titleEn": "Small details"
    },
    {
      "filename": "dark-detail-5.jpeg",
      "alt": "Umelecký detail interiéru salónu.",
      "altEn": "Artistic detail of the salon interior.",
      "title": "Umelecké zátišie",
      "titleEn": "Artistic still life"
    },
    {
      "filename": "dark-detail-6.jpeg",
      "alt": "Detail nábytku a vybavenia v tmavom vyhotovení.",
      "altEn": "Detail of furniture and equipment in dark finish.",
      "title": "Vybavenie salónu",
      "titleEn": "Salon equipment"
    }
  ]
}
